nn_builder/Overall_Base_Network.py
nn_builder/__init__.py
nn_builder/pytorch/Base_Network.py
nn_builder/pytorch/CNN.py
nn_builder/pytorch/NN.py
nn_builder/pytorch/RNN.py
nn_builder/pytorch/__init__.py
nn_builder/tensorflow/Base_Network.py
nn_builder/tensorflow/CNN.py
nn_builder/tensorflow/NN.py
nn_builder/tensorflow/RNN.py
nn_builder/tensorflow/__init__.py
nn_builder-1.0.5.dist-info/LICENSE
nn_builder-1.0.5.dist-info/METADATA
nn_builder-1.0.5.dist-info/WHEEL
nn_builder-1.0.5.dist-info/top_level.txt
nn_builder-1.0.5.dist-info/RECORD
