Metadata-Version: 2.1
Name: nn-builder
Version: 1.0.5
Summary: Build neural networks in 1 line
Home-page: https://github.com/p-christ/nn_builder
Author: Petros Christodoulou
Author-email: p.christodoulou2@gmail.com
License: UNKNOWN
Platform: UNKNOWN
Classifier: Programming Language :: Python :: 3
Classifier: License :: OSI Approved :: MIT License
Classifier: Operating System :: OS Independent
Requires-Dist: tensorflow (==2.0.0a0)
